{
  "__inputs": [
    {
      "name": "DS_PROMETHEUS",
      "label": "Prometheus",
      "description": "",
      "type": "datasource",
      "pluginId": "prometheus",
      "pluginName": "Prometheus"
    }
  ],
  "__requires": [
    {
      "type": "panel",
      "id": "bargauge",
      "name": "Bar Gauge",
      "version": ""
    },
    {
      "type": "panel",
      "id": "gauge",
      "name": "Gauge",
      "version": ""
    },
    {
      "type": "grafana",
      "id": "grafana",
      "name": "Grafana",
      "version": "6.7.3"
    },
    {
      "type": "panel",
      "id": "graph",
      "name": "Graph",
      "version": ""
    },
    {
      "type": "datasource",
      "id": "prometheus",
      "name": "Prometheus",
      "version": "1.0.0"
    }
  ],
  "annotations": {
    "list": [
      {
        "$$hashKey": "object:180",
        "builtIn": 1,
        "datasource": "-- Grafana --",
        "enable": true,
        "hide": true,
        "iconColor": "rgba(0, 211, 255, 1)",
        "name": "Annotations & Alerts",
        "type": "dashboard"
      }
    ]
  },
  "editable": true,
  "gnetId": null,
  "graphTooltip": 0,
  "id": null,
  "iteration": 1588931707367,
  "links": [],
  "panels": [
    {
      "datasource": "${DS_PROMETHEUS}",
      "description": "i7-7820HQ = 4*100=400%\ni7-7820HQ = 4*2900=11600MHz\n",
      "gridPos": {
        "h": 9,
        "w": 5,
        "x": 0,
        "y": 0
      },
      "id": 2,
      "options": {
        "fieldOptions": {
          "calcs": [
            "mean"
          ],
          "defaults": {
            "mappings": [],
            "max": 400,
            "min": 0,
            "thresholds": {
              "mode": "absolute",
              "steps": [
                {
                  "color": "green",
                  "value": null
                },
                {
                  "color": "#EAB839",
                  "value": 90
                },
                {
                  "color": "red",
                  "value": 200
                }
              ]
            },
            "unit": "percent"
          },
          "overrides": [],
          "values": false
        },
        "orientation": "auto",
        "showThresholdLabels": false,
        "showThresholdMarkers": true
      },
      "pluginVersion": "6.7.3",
      "targets": [
        {
          "expr": "sum(cpu_usage)",
          "instant": true,
          "interval": "",
          "legendFormat": "{{process}}",
          "refId": "A"
        }
      ],
      "timeFrom": null,
      "timeShift": null,
      "title": "Current CPU Usage (4 cores = 400%)",
      "transparent": true,
      "type": "gauge"
    },
    {
      "datasource": "${DS_PROMETHEUS}",
      "gridPos": {
        "h": 9,
        "w": 14,
        "x": 5,
        "y": 0
      },
      "id": 6,
      "interval": "1s",
      "options": {
        "displayMode": "lcd",
        "fieldOptions": {
          "calcs": [
            "mean"
          ],
          "defaults": {
            "mappings": [],
            "max": 100,
            "min": 0,
            "thresholds": {
              "mode": "absolute",
              "steps": [
                {
                  "color": "green",
                  "value": null
                },
                {
                  "color": "#EAB839",
                  "value": 40
                },
                {
                  "color": "red",
                  "value": 80
                }
              ]
            },
            "unit": "percent"
          },
          "overrides": [],
          "values": false
        },
        "orientation": "horizontal",
        "showUnfilled": true
      },
      "pluginVersion": "6.7.3",
      "targets": [
        {
          "expr": "topk(10, cpu_usage)",
          "instant": true,
          "interval": "",
          "legendFormat": "{{process}} ({{pid}})",
          "refId": "A"
        }
      ],
      "timeFrom": null,
      "timeShift": null,
      "title": "Top 10 processes + PID",
      "transparent": true,
      "type": "bargauge"
    },
    {
      "datasource": "${DS_PROMETHEUS}",
      "description": "i7-7820HQ = 4*2900=11600MHz",
      "gridPos": {
        "h": 9,
        "w": 5,
        "x": 19,
        "y": 0
      },
      "id": 4,
      "options": {
        "fieldOptions": {
          "calcs": [
            "mean"
          ],
          "defaults": {
            "mappings": [],
            "max": 11600,
            "min": 0,
            "thresholds": {
              "mode": "absolute",
              "steps": [
                {
                  "color": "green",
                  "value": null
                },
                {
                  "color": "#EAB839",
                  "value": 5800
                },
                {
                  "color": "#E24D42",
                  "value": 9000
                }
              ]
            },
            "title": "MHz",
            "unit": "none"
          },
          "overrides": [],
          "values": false
        },
        "orientation": "auto",
        "showThresholdLabels": false,
        "showThresholdMarkers": true
      },
      "pluginVersion": "6.7.3",
      "targets": [
        {
          "expr": "sum(cpu_usage)*2900/100",
          "instant": true,
          "interval": "",
          "legendFormat": "{{process}}",
          "refId": "A"
        }
      ],
      "timeFrom": null,
      "timeShift": null,
      "title": "Current CPU Usage",
      "transparent": true,
      "type": "gauge"
    },
    {
      "aliasColors": {},
      "bars": false,
      "dashLength": 10,
      "dashes": false,
      "datasource": "${DS_PROMETHEUS}",
      "fill": 1,
      "fillGradient": 1,
      "gridPos": {
        "h": 15,
        "w": 24,
        "x": 0,
        "y": 9
      },
      "hiddenSeries": false,
      "id": 7,
      "interval": "",
      "legend": {
        "alignAsTable": true,
        "avg": true,
        "current": true,
        "max": true,
        "min": false,
        "rightSide": true,
        "show": true,
        "sort": "avg",
        "sortDesc": true,
        "total": false,
        "values": true
      },
      "lines": true,
      "linewidth": 1,
      "nullPointMode": "null as zero",
      "options": {
        "dataLinks": []
      },
      "percentage": false,
      "pluginVersion": "6.7.3",
      "pointradius": 2,
      "points": false,
      "renderer": "flot",
      "seriesOverrides": [],
      "spaceLength": 10,
      "stack": false,
      "steppedLine": false,
      "targets": [
        {
          "expr": "topk(10, cpu_usage)",
          "instant": false,
          "interval": "",
          "legendFormat": "{{process}} ({{pid}})",
          "refId": "A"
        }
      ],
      "thresholds": [],
      "timeFrom": null,
      "timeRegions": [],
      "timeShift": null,
      "title": "Top 10 processes + PID",
      "tooltip": {
        "shared": true,
        "sort": 2,
        "value_type": "individual"
      },
      "transparent": true,
      "type": "graph",
      "xaxis": {
        "buckets": null,
        "mode": "time",
        "name": null,
        "show": true,
        "values": []
      },
      "yaxes": [
        {
          "$$hashKey": "object:73",
          "decimals": null,
          "format": "percent",
          "label": null,
          "logBase": 1,
          "max": null,
          "min": null,
          "show": true
        },
        {
          "$$hashKey": "object:74",
          "format": "percent",
          "label": null,
          "logBase": 1,
          "max": "100",
          "min": "0",
          "show": false
        }
      ],
      "yaxis": {
        "align": false,
        "alignLevel": null
      }
    }
  ],
  "refresh": "5s",
  "schemaVersion": 22,
  "style": "dark",
  "tags": [],
  "templating": {
    "list": [
      {
        "datasource": "Prometheus",
        "filters": [],
        "hide": 0,
        "label": "Filters",
        "name": "AdhocFilters",
        "skipUrlSync": false,
        "type": "adhoc"
      }
    ]
  },
  "time": {
    "from": "now-5m",
    "to": "now"
  },
  "timepicker": {
    "refresh_intervals": [
      "5s",
      "10s",
      "30s",
      "1m",
      "5m",
      "15m",
      "30m",
      "1h",
      "2h",
      "1d"
    ]
  },
  "timezone": "",
  "title": "MacOS processes",
  "uid": "l4-L6X6Zk",
  "variables": {
    "list": []
  },
  "version": 20
}